{
    "users": {
        "1": {
            "login": "wojtek",
            "password": "12"
        },
        "2": {
            "login": "adam",
            "password": "oop"
        },
        "3": {
            "login": "andrzej",
            "password": "pylint12"
        },
        "4": {
            "login": "kasia",
            "password": "pep8"
        },
        "5": {
            "login": "aneta",
            "password": "rubyonrails"
        },
        "6": {
            "login": "test",
            "password": "test"
        }
    }
}